{
  "@context": "http://iiif.io/api/presentation/3/context.json",
  "id": "https://scholarbo.github.io/soseki-manuscripts/manifests/manifest-136-w01.json",
  "type": "Manifest",
  "label": {
    "ja": [
      "136. 〔無題〕大正五年八月十五日"
    ]
  },
  "metadata": [
    {
      "label": {
        "ja": [
          "作品ID"
        ]
      },
      "value": {
        "ja": [
          "136"
        ]
      }
    },
    {
      "label": {
        "ja": [
          "作品名"
        ]
      },
      "value": {
        "ja": [
          "136. 〔無題〕大正五年八月十五日"
        ]
      }
    },
    {
      "label": {
        "ja": [
          "Witness"
        ]
      },
      "value": {
        "ja": [
          "w01"
        ]
      }
    },
    {
      "label": {
        "ja": [
          "source"
        ]
      },
      "value": {
        "ja": [
          "東北大学附属図書館漱石文庫蔵"
        ]
      }
    },
    {
      "label": {
        "ja": [
          "date_year"
        ]
      },
      "value": {
        "ja": [
          "1916"
        ]
      }
    },
    {
      "label": {
        "ja": [
          "date_month"
        ]
      },
      "value": {
        "ja": [
          "1916-08"
        ]
      }
    },
    {
      "label": {
        "ja": [
          "date_day"
        ]
      },
      "value": {
        "ja": [
          "1916-08-15"
        ]
      }
    }
  ],
  "items": [
    {
      "id": "https://scholarbo.github.io/soseki-manuscripts/manifests/manifest-136-w01.json/canvas-136-w01",
      "type": "Canvas",
      "width": 1200,
      "height": 1600,
      "label": {
        "ja": [
          "136 第1頁"
        ]
      },
      "items": [
        {
          "id": "https://scholarbo.github.io/soseki-manuscripts/manifests/manifest-136-w01.json/canvas-136-w01/page",
          "type": "AnnotationPage",
          "items": [
            {
              "id": "https://scholarbo.github.io/soseki-manuscripts/manifests/manifest-136-w01.json/canvas-136-w01/annotation",
              "type": "Annotation",
              "motivation": "painting",
              "target": "https://scholarbo.github.io/soseki-manuscripts/manifests/manifest-136-w01.json/canvas-136-w01",
              "body": {
                "id": "https://scholarbo.github.io/soseki-manuscripts/images/136-w01.jpg",
                "type": "Image",
                "format": "image/jpeg",
                "width": 1200,
                "height": 1600
              }
            }
          ]
        }
      ]
    }
  ],
  "summary": {
    "ja": [
      "【原文】\n五十年来処士分\n豈期高踏自離群\n蓽門不杜貧如道\n茅屋偶空交似雲\n天日蒼茫誰有賦\n太虛寥廓我無文\n慇懃寄語寒山子\n饒舌松風独待君"
    ]
  }
}