{
  "@context": "http://iiif.io/api/presentation/3/context.json",
  "id": "https://scholarbo.github.io/soseki-manuscripts/manifests/manifest-052.json",
  "type": "Manifest",
  "label": {
    "ja": [
      "052. 〔無題〕明治二十七年三月九日"
    ]
  },
  "metadata": [
    {
      "label": {
        "ja": [
          "題名"
        ]
      },
      "value": {
        "ja": [
          "052. 〔無題〕明治二十七年三月九日"
        ]
      }
    },
    {
      "label": {
        "ja": [
          "制作日"
        ]
      },
      "value": {
        "ja": [
          "1894-03-09"
        ]
      }
    },
    {
      "label": {
        "ja": [
          "漢詩本文"
        ]
      },
      "value": {
        "ja": [
          "52.〔無題〕　明治二十七年三月九日<br/>閑却花紅柳緑春　　閑却す　花紅柳緑の春<br/>江楼何暇酔芳醇　　江楼　何ぞ芳醇に酔うに暇あらん<br/>猶憐病子多情意　　猶お憐れむ　病子情意多く<br/>独倚禅牀夢美人　　独り禅牀に倚りて美人を夢むるを"
        ]
      }
    },
    {
      "label": {
        "ja": [
          "本文・訓読"
        ]
      },
      "value": {
        "ja": [
          "52.〔無題〕　明治二十七年三月九日<br/>閑却花紅柳緑春　　閑却す　花紅柳緑の春<br/>江楼何暇酔芳醇　　江楼　何ぞ芳醇に酔うに暇あらん<br/>猶憐病子多情意　　猶お憐れむ　病子情意多く<br/>独倚禅牀夢美人　　独り禅牀に倚りて美人を夢むるを"
        ]
      }
    }
  ],
  "items": [
    {
      "id": "https://scholarbo.github.io/soseki-manuscripts/manifests/canvas-052",
      "type": "Canvas",
      "label": {
        "ja": [
          "052. 〔無題〕明治二十七年三月九日"
        ]
      },
      "height": 1600,
      "width": 1200,
      "items": [
        {
          "id": "https://scholarbo.github.io/soseki-manuscripts/manifests/page-052",
          "type": "AnnotationPage",
          "items": [
            {
              "id": "https://scholarbo.github.io/soseki-manuscripts/manifests/anno-052",
              "type": "Annotation",
              "motivation": "painting",
              "body": {
                "id": "https://scholarbo.github.io/soseki-manuscripts/iiif/images/052.jpg",
                "type": "Image",
                "format": "image/jpg",
                "height": 1600,
                "width": 1200
              },
              "target": "https://scholarbo.github.io/soseki-manuscripts/manifests/canvas-052"
            }
          ]
        }
      ]
    }
  ]
}