{
  "@context": "http://iiif.io/api/presentation/3/context.json",
  "id": "https://scholarbo.github.io/soseki-manuscripts/manifests/manifest-216-mitei-08.json",
  "type": "Manifest",
  "label": {
    "ja": [
      "216. 未定稿八"
    ]
  },
  "metadata": [],
  "items": [
    {
      "id": "https://scholarbo.github.io/soseki-manuscripts/canvas/216-mitei-08/p1",
      "type": "Canvas",
      "label": {
        "ja": [
          "216. 未定稿八"
        ]
      },
      "height": 3024,
      "width": 4032,
      "items": [
        {
          "id": "https://scholarbo.github.io/soseki-manuscripts/page/216-mitei-08/p1",
          "type": "AnnotationPage",
          "items": [
            {
              "id": "https://scholarbo.github.io/soseki-manuscripts/annotation/216-mitei-08/p1-image",
              "type": "Annotation",
              "motivation": "painting",
              "body": {
                "id": "https://scholarbo.github.io/soseki-manuscripts/images/216-mitei-08.jpg",
                "type": "Image",
                "format": "image/jpeg",
                "height": 3024,
                "width": 4032
              },
              "target": "https://scholarbo.github.io/soseki-manuscripts/canvas/216-mitei-08/p1"
            }
          ]
        }
      ]
    }
  ]
}